flightplans/__init__.py
flightplans/examples.py
flightplans/flightplans.py
flightplans/data/__init__.py
flightplans/utils/__init__.py
flightplans-0.1.0.dist-info/LICENSE
flightplans-0.1.0.dist-info/METADATA
flightplans-0.1.0.dist-info/WHEEL
flightplans-0.1.0.dist-info/top_level.txt
flightplans-0.1.0.dist-info/RECORD
