Metadata-Version: 2.1
Name: flightplans
Version: 0.1.0
Summary: Python package flightplans
Home-page: https://github.com/erdogant/flightplans
Download-URL: https://github.com/erdogant/flightplans/archive/0.1.0.tar.gz
Author: Erdogan Taskesen
Author-email: erdogant@gmail.com
License: UNKNOWN
Platform: UNKNOWN
Classifier: Programming Language :: Python :: 3
Classifier: License :: OSI Approved
Classifier: Operating System :: OS Independent
Requires-Python: >=3
License-File: LICENSE
Requires-Dist: matplotlib
Requires-Dist: numpy
Requires-Dist: pandas
Requires-Dist: tqdm
